bussing/__init__.py
bussing/busses.py
bus-0.0.1.dist-info/LICENSE
bus-0.0.1.dist-info/METADATA
bus-0.0.1.dist-info/WHEEL
bus-0.0.1.dist-info/top_level.txt
bus-0.0.1.dist-info/RECORD
