Metadata-Version: 2.1
Name: bus
Version: 0.0.1
Summary: Aggregate JSON data together
Home-page: https://github.com/CoburnJoe/bus
Author: Joe Coburn
Author-email: joe@scholarpack.com
License: UNKNOWN
Platform: UNKNOWN
Classifier: Development Status :: 2 - Pre-Alpha  
Classifier: Programming Language :: Python :: 3
Classifier: License :: OSI Approved :: GNU Lesser General Public License v3 (LGPLv3)
Classifier: Operating System :: OS Independent
Requires-Python: >=3.6
